
<annotation>
    <folder>Sea turtles</folder>
    <filename>8c210454c669bc16.jpg</filename>
    <path>/path/to/the/file/8c210454c669bc16.jpg</path>
    <source>
        <database>Unknown</database>
    </source>
    <size>
        <width>1024</width>
        <height>768</height>
        <depth>3</depth>
    </size>
    <segmented>0</segmented>
    <object>
        <name>Sea turtles</name>
        <pose>Unspecified</pose>
        <truncated>0</truncated>
        <difficult>0</difficult>
        <bndbox>
            <xmin>174</xmin>
            <ymin>241</ymin>
            <xmax>366</xmax>
            <ymax>378</ymax>
        </bndbox>
</object>
<object>
        <name>Sea turtles</name>
        <pose>Unspecified</pose>
        <truncated>0</truncated>
        <difficult>0</difficult>
        <bndbox>
            <xmin>192</xmin>
            <ymin>399</ymin>
            <xmax>361</xmax>
            <ymax>500</ymax>
        </bndbox>
</object>
<object>
        <name>Sea turtles</name>
        <pose>Unspecified</pose>
        <truncated>0</truncated>
        <difficult>0</difficult>
        <bndbox>
            <xmin>293</xmin>
            <ymin>467</ymin>
            <xmax>437</xmax>
            <ymax>593</ymax>
        </bndbox>
</object>
<object>
        <name>Sea turtles</name>
        <pose>Unspecified</pose>
        <truncated>0</truncated>
        <difficult>0</difficult>
        <bndbox>
            <xmin>314</xmin>
            <ymin>186</ymin>
            <xmax>520</xmax>
            <ymax>276</ymax>
        </bndbox>
</object>
<object>
        <name>Sea turtles</name>
        <pose>Unspecified</pose>
        <truncated>0</truncated>
        <difficult>0</difficult>
        <bndbox>
            <xmin>432</xmin>
            <ymin>469</ymin>
            <xmax>589</xmax>
            <ymax>611</ymax>
        </bndbox>
</object>
<object>
        <name>Sea turtles</name>
        <pose>Unspecified</pose>
        <truncated>0</truncated>
        <difficult>0</difficult>
        <bndbox>
            <xmin>455</xmin>
            <ymin>246</ymin>
            <xmax>755</xmax>
            <ymax>424</ymax>
        </bndbox>
</object>
<object>
        <name>Sea turtles</name>
        <pose>Unspecified</pose>
        <truncated>0</truncated>
        <difficult>0</difficult>
        <bndbox>
            <xmin>531</xmin>
            <ymin>75</ymin>
            <xmax>661</xmax>
            <ymax>231</ymax>
        </bndbox>
</object>
<object>
        <name>Sea turtles</name>
        <pose>Unspecified</pose>
        <truncated>0</truncated>
        <difficult>0</difficult>
        <bndbox>
            <xmin>614</xmin>
            <ymin>459</ymin>
            <xmax>760</xmax>
            <ymax>591</ymax>
        </bndbox>
</object>
<object>
        <name>Sea turtles</name>
        <pose>Unspecified</pose>
        <truncated>0</truncated>
        <difficult>0</difficult>
        <bndbox>
            <xmin>717</xmin>
            <ymin>90</ymin>
            <xmax>894</xmax>
            <ymax>193</ymax>
        </bndbox>
</object>
<object>
        <name>Sea turtles</name>
        <pose>Unspecified</pose>
        <truncated>0</truncated>
        <difficult>0</difficult>
        <bndbox>
            <xmin>789</xmin>
            <ymin>473</ymin>
            <xmax>970</xmax>
            <ymax>597</ymax>
        </bndbox>
</object>
<object>
        <name>Sea turtles</name>
        <pose>Unspecified</pose>
        <truncated>0</truncated>
        <difficult>0</difficult>
        <bndbox>
            <xmin>800</xmin>
            <ymin>195</ymin>
            <xmax>991</xmax>
            <ymax>311</ymax>
        </bndbox>
</object>
<object>
        <name>Sea turtles</name>
        <pose>Unspecified</pose>
        <truncated>0</truncated>
        <difficult>0</difficult>
        <bndbox>
            <xmin>802</xmin>
            <ymin>327</ymin>
            <xmax>987</xmax>
            <ymax>463</ymax>
        </bndbox>
</object>

</annotation>
