
<annotation>
    <folder>Sea turtles</folder>
    <filename>9528449e63b6733e.jpg</filename>
    <path>/path/to/the/file/9528449e63b6733e.jpg</path>
    <source>
        <database>Unknown</database>
    </source>
    <size>
        <width>1024</width>
        <height>768</height>
        <depth>3</depth>
    </size>
    <segmented>0</segmented>
    <object>
        <name>Sea turtles</name>
        <pose>Unspecified</pose>
        <truncated>0</truncated>
        <difficult>0</difficult>
        <bndbox>
            <xmin>92</xmin>
            <ymin>272</ymin>
            <xmax>757</xmax>
            <ymax>487</ymax>
        </bndbox>
</object>

</annotation>
